setup.py
pqb/__init__.py
pqb/expressions.py
pqb/grouping.py
pqb/queries.py
pqb/statements.py
pqb.egg-info/PKG-INFO
pqb.egg-info/SOURCES.txt
pqb.egg-info/dependency_links.txt
pqb.egg-info/not-zip-safe
pqb.egg-info/top_level.txt