Metadata-Version: 1.0
Name: pqb
Version: 0.0.2
Summary: Simple SQL Query Builder
Home-page: http://github.com/josegomezr/pqb
Author: Jose Gomez
Author-email: 1josegomezr@gmail.com
License: MIT
Platform: UNKNOWN
